jsii_sample/__init__.py
jsii_sample/py.typed
jsii_sample/_jsii/__init__.py
jsii_sample/_jsii/jsii-sample@1.5.9.jsii.tgz
jsii_sample-1.5.9.dist-info/METADATA
jsii_sample-1.5.9.dist-info/WHEEL
jsii_sample-1.5.9.dist-info/top_level.txt
jsii_sample-1.5.9.dist-info/RECORD
