Metadata-Version: 2.1
Name: jsii-sample
Version: 1.5.9
Summary: hello, world
Home-page: https://git-codecommit.us-east-1.amazonaws.com/v1/repos/jsii-sample
Author: Amazon Web Services
License: UNKNOWN
Project-URL: Source, https://git-codecommit.us-east-1.amazonaws.com/v1/repos/jsii-sample
Platform: UNKNOWN
Requires-Python: >=3.6
Requires-Dist: jsii (~=0.20.2)
Requires-Dist: publication (>=0.0.3)
